jpwr/__init__.py
jpwr/clitool.py
jpwr/ctxmgr.py
jpwr/gpu/__init__.py
jpwr/gpu/pynvml.py
jpwr/gpu/rocm.py
jpwr/ipu/__init__.py
jpwr/ipu/gc.py
jpwr/sys/__init__.py
jpwr/sys/gh.py
jpwr-0.0.10.dist-info/METADATA
jpwr-0.0.10.dist-info/WHEEL
jpwr-0.0.10.dist-info/entry_points.txt
jpwr-0.0.10.dist-info/licenses/LICENSE
jpwr-0.0.10.dist-info/RECORD
