Metadata-Version: 2.4
Name: jpwr
Version: 0.0.10
Summary: JSC energy/power measurement tool
Project-URL: Homepage, https://github.com/TBD/jpwr
Project-URL: Issues, https://github.com/TBD/jpwr/issues
Author-email: Stepan Nassyr <s.nassyr@fz-juelich.de>
License-File: LICENSE
Classifier: License :: OSI Approved :: GNU General Public License v3 (GPLv3)
Classifier: Operating System :: OS Independent
Classifier: Programming Language :: Python :: 3
Requires-Python: >=3.8
Requires-Dist: numpy
Requires-Dist: pandas
Provides-Extra: mpi
Requires-Dist: mpi4py; extra == 'mpi'
Provides-Extra: pynvml
Requires-Dist: nvidia-ml-py; extra == 'pynvml'
